README.md
setup.py
ttax/__init__.py
ttax/autodiff.py
ttax/autodiff_test.py
ttax/base_class.py
ttax/compile.py
ttax/compile_test.py
ttax/decompositions.py
ttax/decompositions_test.py
ttax/ops.py
ttax/ops_test.py
ttax/random_.py
ttax/riemannian.py
ttax/riemannian_test.py
ttax/utils.py
ttax.egg-info/PKG-INFO
ttax.egg-info/SOURCES.txt
ttax.egg-info/dependency_links.txt
ttax.egg-info/not-zip-safe
ttax.egg-info/requires.txt
ttax.egg-info/top_level.txt