Metadata-Version: 1.0
Name: ttax
Version: 0.0.2
Summary: Tensor Train decomposition on Jax
Home-page: https://github.com/fasghq/ttax
Author: Alexander Novikov and Dmitry Belousov
Author-email: sasha.v.novikov@gmail.com
License: MIT
Platform: UNKNOWN
